darli/__init__.py
darli/backend/__init__.py
darli/backend/_base.py
darli/backend/_casadi.py
darli/backend/_pinocchio.py
darli/backend/liecasadi/__init__.py
darli/backend/liecasadi/quaternion.py
darli/backend/liecasadi/so3.py
darli/backend/liecasadi/hints/__init__.py
darli/model/__init__.py
darli/model/_base.py
darli/model/_body.py
darli/model/_contact.py
darli/model/_model.py
darli/model/functional/__init__.py
darli/model/functional/_body.py
darli/model/functional/_contact.py
darli/model/functional/_model.py
darli/parametric/__init__.py
darli/parametric/_functional.py
darli/parametric/_model.py
darli/robots/__init__.py
darli/robots/_robots.py
darli/state_space/__init__.py
darli/state_space/_base.py
darli/state_space/_casadi.py
darli/state_space/_common.py
darli/state_space/_functional.py
darli/state_space/_pinocchio.py
darli/state_space/_state_space.py
darli/state_space/integrators/__init__.py
darli/state_space/integrators/_base.py
darli/state_space/integrators/_fwd_euler.py
darli/state_space/integrators/_mid_point.py
darli/state_space/integrators/_rk4.py
darli/utils/arrays/__init__.py
darli/utils/arrays/_arraylike.py
darli/utils/arrays/_casadi.py
darli/utils/arrays/_numpy.py
darli/utils/quaternions/__init__.py
darli/utils/quaternions/_quaternions.py
darli-0.4.3.dist-info/METADATA
darli-0.4.3.dist-info/WHEEL
darli-0.4.3.dist-info/top_level.txt
darli-0.4.3.dist-info/RECORD
