Metadata-Version: 2.1
Name: darli
Version: 0.4.3
Summary: The DARLi is a Python 3 library that supports both numerical and symbolical computations of open loop articulated robots provided urdf file.
Author: Lev Kozlov, Simeon Nedelchev
Project-URL: homepage, https://github.com/simeon-ned/darli
Project-URL: repository, https://github.com/simeon-ned/darli.git
Requires-Python: >=3.9
Requires-Dist: cmeel-casadi-kin-dyn >=1.6.14
Provides-Extra: dev
Requires-Dist: pre-commit ; extra == 'dev'
